libredr-0.0.22.dist-info/METADATA
libredr-0.0.22.dist-info/WHEEL
libredr-0.0.22.dist-info/licenses/LICENSE
libredr/__init__.py
libredr/camera/__init__.py
libredr/camera/cube.py
libredr/camera/equirectangular.py
libredr/libredr.abi3.so
libredr/torch/__init__.py
libredr/torch/light_source/__init__.py
libredr/torch/nn/functional.py
libredr/torch/ray_tracing.py
libredr-0.0.22.dist-info/RECORD
