Metadata-Version: 2.4
Name: libredr
Version: 0.0.22
Classifier: Development Status :: 3 - Alpha
Classifier: Programming Language :: Python
Classifier: Programming Language :: Rust
Classifier: License :: OSI Approved :: GNU Affero General Public License v3 or later (AGPLv3+)
Requires-Dist: numpy
Requires-Dist: torch ; extra == 'torch'
Provides-Extra: torch
License-File: LICENSE
Summary: LibreDR is an open-source ray-tracing differentiable renderer
Home-Page: https://codeberg.org/ybh1998/LibreDR/
Author: Bohan Yu
Author-email: ybh1998@protonmail.com
Requires-Python: >=3.8
Project-URL: homepage, https://codeberg.org/ybh1998/LibreDR
Project-URL: documentation, https://ybh1998.codeberg.page/LibreDR/
